luxbin_light_converter.py
luxbin_compiler/__init__.py
luxbin_compiler/analyzer.py
luxbin_compiler/ast_nodes.py
luxbin_compiler/builtins.py
luxbin_compiler/cli.py
luxbin_compiler/codegen.py
luxbin_compiler/errors.py
luxbin_compiler/lexer.py
luxbin_compiler/parser.py
luxbin_compiler/vm.py
luxbin_light_language-1.0.0.dist-info/licenses/LICENSE
web_translator/__init__.py
web_translator/__main__.py
web_translator/cli.py
web_translator/code_to_lux.py
web_translator/content_to_lll.py
web_translator/css_extractor.py
web_translator/fetcher.py
web_translator/html_parser.py
web_translator/js_extractor.py
web_translator/output.py
luxbin_light_language-1.0.0.dist-info/METADATA
luxbin_light_language-1.0.0.dist-info/WHEEL
luxbin_light_language-1.0.0.dist-info/entry_points.txt
luxbin_light_language-1.0.0.dist-info/top_level.txt
luxbin_light_language-1.0.0.dist-info/RECORD
