Metadata-Version: 2.4
Name: luxbin-light-language
Version: 1.0.0
Summary: Universal photonic communication protocol for computers using color light wavelengths
Author: Nichole Christie
License: MIT
Project-URL: Homepage, https://github.com/nichechristie/luxbin-light-language
Classifier: Programming Language :: Python :: 3
Classifier: Programming Language :: Python :: 3.10
Classifier: Programming Language :: Python :: 3.11
Classifier: Programming Language :: Python :: 3.12
Classifier: License :: OSI Approved :: MIT License
Classifier: Operating System :: OS Independent
Requires-Python: >=3.10
License-File: LICENSE
Provides-Extra: quantum
Requires-Dist: qiskit>=1.0.0; extra == "quantum"
Requires-Dist: qiskit-ibm-runtime>=0.17.0; extra == "quantum"
Requires-Dist: numpy>=1.24.0; extra == "quantum"
Provides-Extra: server
Requires-Dist: aiohttp>=3.9.0; extra == "server"
Provides-Extra: crypto
Requires-Dist: cryptography>=41.0.0; extra == "crypto"
Provides-Extra: all
Requires-Dist: luxbin-light-language[crypto,quantum,server]; extra == "all"
Requires-Dist: clang>=17.0.0; extra == "all"
Dynamic: license-file
